bayesian_priors/__init__.py
bayesian_priors/blurb_beta.py
bayesian_priors/blurb_cauchy.py
bayesian_priors/blurb_exponential.py
bayesian_priors/blurb_gamma.py
bayesian_priors/blurb_gumbel.py
bayesian_priors/blurb_invgamma.py
bayesian_priors/blurb_lognormal.py
bayesian_priors/blurb_normal.py
bayesian_priors/blurb_pareto.py
bayesian_priors/blurb_studentt.py
bayesian_priors/blurb_weibull.py
bayesian_priors/prior_dashboard_builder.py
bayesian_priors/prior_inverse_search.py
bayesian_priors-0.0.1.dist-info/METADATA
bayesian_priors-0.0.1.dist-info/WHEEL
bayesian_priors-0.0.1.dist-info/top_level.txt
bayesian_priors-0.0.1.dist-info/RECORD
