Metadata-Version: 2.1
Name: bayesian-priors
Version: 0.0.1
Summary: Bayesian-priors is a package for visualizing prior distributions in the context of bayesian inference.
Home-page: UNKNOWN
Author: Rosita Fu
Author-email: rosita.fu99@gmail.com
License: MIT
Platform: UNKNOWN
Classifier: Programming Language :: Python :: 3
Classifier: License :: OSI Approved :: MIT License
Requires-Dist: numpy
Requires-Dist: scipy
Requires-Dist: pandas
Requires-Dist: bokeh
Requires-Dist: panel
